actmc/__init__.py
actmc/chunk.py
actmc/client.py
actmc/errors.py
actmc/gateway.py
actmc/math.py
actmc/protocol.py
actmc/py.typed
actmc/state.py
actmc/tcp.py
actmc/user.py
actmc/utils.py
actmc/entities/__init__.py
actmc/entities/ambient.py
actmc/entities/animals.py
actmc/entities/aquatic.py
actmc/entities/blocks.py
actmc/entities/dragons.py
actmc/entities/entity.py
actmc/entities/flying.py
actmc/entities/golems.py
actmc/entities/hanging.py
actmc/entities/illagers.py
actmc/entities/misc.py
actmc/entities/monsters.py
actmc/entities/player.py
actmc/entities/projectiles.py
actmc/entities/tameable.py
actmc/entities/vehicles.py
actmc/entities/villagers.py
actmc/ext/tasks/__init__.py
actmc/types/__init__.py
actmc/types/advancement.py
actmc/types/entities.py
actmc/ui/__init__.py
actmc/ui/actionbar.py
actmc/ui/advancement.py
actmc/ui/border.py
actmc/ui/bossbar.py
actmc/ui/chat.py
actmc/ui/gui.py
actmc/ui/scoreboard.py
actmc/ui/tablist.py
actmc-1.12.2.post3.dist-info/LICENSE
actmc-1.12.2.post3.dist-info/METADATA
actmc-1.12.2.post3.dist-info/WHEEL
actmc-1.12.2.post3.dist-info/top_level.txt
actmc-1.12.2.post3.dist-info/RECORD
