Metadata-Version: 2.1
Name: actmc
Version: 1.12.2.post3
Summary: An async Python client for Minecraft 1.12.2 Java Edition servers (offline-mode)
Author-email: Snifo <Snifo@mail.com>
License: MIT
Project-URL: Homepage, https://github.com/mrsnifo/actmc
Project-URL: Documentation, https://actmc.readthedocs.io/latest/
Project-URL: Issue tracker, https://github.com/mrsnifo/actmc/issues
Project-URL: Repository, https://github.com/mrsnifo/actmc
Keywords: bot,minecraft,minecraft-protocol,minecraft-bot
Classifier: Development Status :: 5 - Production/Stable
Classifier: License :: OSI Approved :: MIT License
Classifier: Intended Audience :: Developers
Classifier: Natural Language :: English
Classifier: Operating System :: OS Independent
Classifier: Programming Language :: Python :: 3.12
Classifier: Programming Language :: Python :: 3.13
Classifier: Topic :: Games/Entertainment
Classifier: Topic :: Software Development :: Libraries
Classifier: Topic :: Software Development :: Libraries :: Python Modules
Classifier: Topic :: Utilities
Classifier: Typing :: Typed
Classifier: Framework :: AsyncIO
Requires-Python: <4.0,>=3.12.0
License-File: LICENSE
